Workbook

Sheet Instruções
A6: INSTRUÇÕES DE USO
A9: FINALIDADE
B10: Ferramenta elaborada para apoiar a análise técnica da precificação de obras em estudos, modelagens, projetos, editais ou contratos.
B11: Não se destina a um único projeto e serve como base padronizada.
A13: FLUXO DE PREENCHIMENTO
B14: 1. Aba 0 (Capa) — identificação do preenchimento: caso analisado, analista, data.
B15: 2. Aba 1 (Identificação) — cadastro dos dados do projeto, órgão, modalidade, fase e documentos examinados.
B16: 3. Aba 2 (Metodologia) — metodologias utilizadas e registre parâmetros (data-base, regionalização, atualização, composições, fatores adicionais).
B17: 4. Aba 3 (Referências) — referência de preços identificadas e adequação ao objeto.
B18: 5. Aba 4 (Componentes) — métricas globais (valor total, m², BDI) e as parcelas do custo.
B19: 6. Aba 5 (Justificativa) — síntese da justificativas identificadas e avaliação de qualidade.
B20: 7. Aba 6 (Análise Crítica) — checklist avaliativo de maturidade metodológica.
B21: 8. Aba 7 (Síntese) — elaboração da síntese interpretativa e do parecer global.
B22: 9. Aba 8 (Relatório) — texto gerado serve como base para o relatório.
A24: CAMPOS OBRIGATÓRIOS
B25: Os campos em fundo amarelo indicam preenchimento obrigatório.
B26: Campos com lista suspensa devem ser preenchidos selecionando uma das opções disponíveis.
A28: USO DAS FÓRMULAS
B29: Não altere as fórmulas; se precisar adaptar, faça-o em cópia do arquivo para preservar o modelo.
A32: BOAS PRÁTICAS
B33: Preencha seções descritivas com frases objetivas e claras, pois o texto segue para o relatório automatizado.
B34: Indique sempre a fonte documental das informações (processo, página, item) para rastreabilidade.
B35: Ao concluir, revise a aba 8 e edite livremente o texto-base antes da emissão do relatório.
B36: Salve o arquivo preenchido com identificação do caso (ex.: precificacao_obras_<projeto>_<data>.xlsx).
A38: APROVEITAMENTO PARA O RELATÓRIO
B39: O texto da aba 8 contempla: identificação do caso, metodologia, referências, parâmetros, justificativa, análise crítica, fragilidades, recomendações e conclusão.
B40: Os indicadores automatizados (conformidade e risco) podem ser utilizados como anexo ao parecer.
A42: MANUTENÇÃO DA FERRAMENTA
B43: Recomenda-se revisão periódica da ferramenta para incorporar melhorias.
A45: REFERÊNCIAS NORMATIVAS E TÉCNICAS
B46: - Lei federal nº 14.133/2021 (Nova Lei de Licitações e Contratos Administrativos); - Lei federal nº 11.079/2004 (institui normas gerais para licitação e contratação de parceria público-privada); - Lei estadual nº 12.234/2005 (institui o Programa de Parcerias Público-Privadas do Estado do Rio Grande do Sul); - Acórdãos do Tribunal de Contas da União sobre BDI e orçamentação de obras públicas, com destaque para o Acórdão nº 2.622/2013 - Plenário (parâmetros de BDI por tipologia de obra) e o Acórdão nº 2.369/2011 - Plenário; - Manual de Metodologias e Conceitos do SINAPI (Sistema Nacional de Pesquisa de Custos e Índices da Construção Civil, mantido pela Caixa Econômica Federal e IBGE); e - Manual de Custos de Infraestrutura de Transportes do DNIT (SICRO — Sistema de Custos Referenciais de Obras).

Sheet 0. Capa
B7: ANÁLISE DE PRECIFICAÇÃO DE OBRAS
B8: Checklist e Roteiro Analítico para Avaliação Técnica de Precificação em Projetos, Modelagens, Editais e Contratos
B11: IDENTIFICAÇÃO DO PREENCHIMENTO
B12: Obra/Projeto analisado:
B13: Órgão/Entidade responsável:
B14: Responsável(is) pela Análise:
B15: Unidade:
B16: Data de início da análise:
B17: Data de conclusão da análise:
B18: Versão do preenchimento:
B20: SUMÁRIO DA FERRAMENTA
B21: Aba 1 | C21: Identificação do caso analisado
B22: Aba 2 | C22: Metodologia de precificação
B23: Aba 3 | C23: Referências e bases de preços
B24: Aba 4 | C24: Parâmetros e componentes do custo
B25: Aba 5 | C25: Justificativa técnica
B26: Aba 6 | C26: Análise crítica da consistência
B27: Aba 7 | C27: Síntese conclusiva
B28: Aba 8 | C28: Relatório automatizado (base)
B30: LEGENDA DE CORES
C31: Campo de preenchimento
C32: Conformidade
C33: Ressalva
C34: Risco ou fragilidade

Sheet 1. Identificação
A6: ABA 1 — IDENTIFICAÇÃO DO CASO ANALISADO
A7: Registro dos dados básicos do objeto submetido à análise. Campos em amarelo são de preenchimento obrigatório.
A9: 1.1 IDENTIFICAÇÃO GERAL
B10: Nome do projeto / estudo / contratação:
B11: Objeto resumido:
B12: Órgão ou entidade responsável:
B13: Unidade demandante / requisitante:
B14: Número do processo / expediente (PROA,SEI,...):
B15: Modalidade contratual (PPP, concessão, obra direta, RDC,...):
A17: 1.2 CARACTERIZAÇÃO DO OBJETO
B18: Tipo de empreendimento (setor / função):
B19: Natureza:
B20: Área estimada (m²):
B21: Valor total da obra no documento analisado (R$):
B22: Prazo estimado de execução:
B23: Localização:
A25: 1.3 FASE E FONTE DOCUMENTAL
B26: Fase do projeto analisada:
B27: Documentos analisados (referências):
B28: Data-base dos preços:
B29: Documento de origem da memória de cálculo:
B30: Responsável técnico pela precificação (se identificado):
B31: Existe ART/RRT anexado ou referenciado? (Detalhar)
A33: 1.4 OBSERVAÇÕES PRELIMINARES
B34: Observações/contexto relevante para a análise:

Sheet 2. Metodologia
A6: ABA 2 — METODOLOGIA DE PRECIFICAÇÃO
A7: Registro das metodologias utilizadas para mensurar o valor das obras: bases de preços, data-base, regionalização, atualização monetária, benchmarks, composições unitárias ou fatores adicionais.
A9: 2.1 METODOLOGIAS UTILIZADAS (assinalar todas as aplicáveis)
B10: Metodologia / Referência | C10: Utilizada? | D10: Detalhamento (base, versão, local aplicado) | E10: Observações críticas
B11: SINAPI — Sistema Nacional de Pesquisa de Custos e Índices
B12: SICRO — Sistema de Custos Referenciais de Obras (DNIT)
B13: CUB/SINDUSCON — Custo Unitário Básico da Construção
B14: Composições próprias do órgão/ente
B15: Valores de contratações similares (preços contratados)
B16: Cotações de mercado (coletas de preços)
B17: Orçamento consultivo / consultoria especializada
B18: Sistema interno do órgão (base própria)
B19: Benchmark setorial / estudos de referência
B20: Metodologia híbrida (combinação)
B21: Outra metodologia (detalhar)
B23: Total de metodologias marcadas como 'Sim': | C23: =COUNTIF(C11:C21,"Sim") -> 0
A25: 2.2 PARÂMETROS METODOLÓGICOS APLICADOS
B26: Data-base dos preços:
B27: Houve regionalização dos preços?
B28: Qual o estado/região adotado como referência?
B29: Houve atualização monetária dos preços?
B30: Qual índice de atualização adotado (IPCA, INCC, IGP-M, etc.)?
B31: Foram utilizados benchmarks de contratações similares?
B32: Foram utilizadas composições unitárias de serviços?
B33: Foram utilizados parâmetros por m² (custo médio)?
B34: Foram adotados fatores adicionais / incrementos / ajustes?
B35: Se sim, descrever fatores adicionais e percentuais:
B36: Há memória de cálculo detalhada disponível?
B37: Há ART/RRT do responsável pela precificação?

Sheet 3. Referências
A6: ABA 3 — REFERÊNCIAS E BASES DE PREÇOS
A7: Registro das bases de preços utilizadas, com data-base, abrangência regional e adequação ao objeto. Permite avaliar se a referência escolhida é compatível com o tipo de obra.
A9: 3.1 BASES DE PREÇOS EMPREGADAS
A10: Item | B10: Base de preços | C10: Data-base | D10: Versão/Tabela | E10: Abrangência regional | F10: Trecho do escopo a que se aplica
A11: 1
A12: 2
A13: 3
A14: 4
A15: 5
A16: 6
A17: 7
A18: 8
A19: 9
A20: 10
A22: 3.2 ANÁLISE DE ADEQUAÇÃO DAS BASES
B23: A(s) base(s) utilizada(s) é(são) compatível(is) com o tipo de obra?
B24: A data-base dos preços é recente ou está adequadamente atualizada?
B25: Houve uso preferencial de referências públicas (SINAPI/SICRO)?
B26: Quando houve uso de cotações de mercado, há no mínimo 3 cotações?
B27: As cotações de mercado apresentam data, origem e responsável?
B28: O uso do CUB (quando aplicável) está acompanhado de incremento justificado?
B29: As bases utilizadas cobrem todo o escopo da obra?

Sheet 4. Componentes
A6: ABA 4 — PARÂMETROS E COMPONENTES DO CUSTO
A7: Registro e avaliação dos componentes que formam o custo total da obra: custo por m², BDI, fundações, projetos, acabamentos, equipamentos, climatização, serviços complementares, infraestrutura externa e demais parcelas.
A9: 4.1 MÉTRICAS GLOBAIS DE PRECIFICAÇÃO
B10: Métrica | C10: Valor apurado | D10: Unidade | E10: Referência/benchmark | F10: Comentários
B11: Valor total da obra | D11: R$
B12: Área total construída/intervencionada | D12: m²
B13: Custo por m² apurado | D13: R$/m²
B14: BDI adotado | D14: %
B15: Taxa de incremento sobre CUB (se aplicável) | D15: %
B16: Contingência / reserva técnica | D16: %
B17: Encargos sociais aplicados | D17: %
B18: Custo direto total | D18: R$
B19: Custo indireto total | D19: R$
A21: 4.2 PARCELAS / COMPONENTES DO CUSTO
B22: Parcela / Componente | C22: Presente? | D22: Valor (R$) | E22: % do total | F22: Observações técnicas
B23: Serviços preliminares e canteiro
B24: Fundações e contenções
B25: Estrutura
B26: Vedações e esquadrias
B27: Instalações elétricas
B28: Instalações hidrossanitárias
B29: Instalações de prevenção e combate a incêndio
B30: Climatização (HVAC)
B31: Elevadores e transporte vertical
B32: Acabamentos e revestimentos
B33: Equipamentos especiais / mobiliário fixo
B34: Infraestrutura externa / urbanização
... B39: Outros serviços complementares
B40: TOTAL DAS PARCELAS INFORMADAS | C40: =COUNTIF(C23:C39,"Sim") -> 0 | D40: =SUM(D23:D39) -> 0 | E40: =SUM(E23:E39) -> 0

Sheet 5. Justificativa
A6: ABA 5 — JUSTIFICATIVA TÉCNICA DA PRECIFICAÇÃO
A7: Transcrição, síntese e avaliação da justificativa técnica apresentada nos documentos analisados. Examina se a justificativa é explícita, suficiente e fundamentada.
A9: 5.1 JUSTIFICATIVAS APRESENTADAS NOS DOCUMENTOS
B10: Tópico | C10: Objeto identificado nos documentos | D10: Justificativa transcrita / sintetizada | E10: Qualidade da justificativa
B11: Justificativa para a escolha da metodologia de precificação | C11: {=IFERROR(_xlfn.TEXTJOIN("; ",TRUE(),_xlfn._xlws.FILTER('2. Metodologia'!B11:B21,'2. Metodologia'!C11:C21="Sim")),"—")} -> —
B12: Justificativa para a escolha da(s) base(s) de preços | C12: {=IFERROR(_xlfn.TEXTJOIN("; ",TRUE(),_xlfn._xlws.FILTER('3. Referências'!B11:B20,'3. Referências'!B11:B20<>"")),"—")} -> —
B13: Justificativa para a data-base adotada | C13: =IF('2. Metodologia'!D26="","—",'2. Metodologia'!D26) -> —
B14: Justificativa para o BDI adotado | C14: =IF('4. Componentes'!C14="","—",'4. Componentes'!C14&"%") -> —
B15: Justificativa para taxa de incremento sobre CUB (se aplicável) | C15: =IF('4. Componentes'!C15="","—",'4. Componentes'!C15&"%") -> —
B16: Justificativa para fatores adicionais, percentuais ou ajustes | C16: =IF('2. Metodologia'!D35="","—",'2. Metodologia'!D35) -> —
B17: Justificativa para parâmetros por m² (quando usados) | C17: =IF('4. Componentes'!C13="","—",'4. Componentes'!C13&" R$/m²") -> —
B18: Justificativa para contingência / reserva técnica | C18: =IF('4. Componentes'!C16="","—",'4. Componentes'!C16&"%") -> —
B19: Justificativa para composições próprias (se houver) | C19: =IF('2. Metodologia'!D14="","—",'2. Metodologia'!D14) -> —
B20: Justificativa para valores de cotação de mercado (se houver) | C20: =IF('2. Metodologia'!D16="","—",'2. Metodologia'!D16) -> —
A22: 5.2 FUNDAMENTAÇÃO DAS JUSTIFICATIVAS APRESENTADAS
B23: As justificativas estão apoiadas em norma ou regulamento?
B24: Quais normas/regulamentos (se aplicável)?
B25: As justificativas estão apoiadas em benchmark externo?
B26: As justificativas estão apoiadas em estudos anteriores?
B27: As justificativas estão apoiadas em experiência institucional?
B28: As justificativas estão apoiadas em premissas próprias explicitadas?
B29: As justificativas citam parecer técnico específico?
A31: 5.3 AVALIAÇÃO GLOBAL DA SUFICIÊNCIA
B32: Avaliação global da suficiência da justificativa apresentada:
B33: Fundamentação da avaliação (síntese do analista):

Sheet 6. Análise Crítica
A6: ABA 6 — ANÁLISE CRÍTICA DA CONSISTÊNCIA METODOLÓGICA
A7: Checklist orientado a evidenciar clareza metodológica, rastreabilidade dos cálculos, compatibilidade da referência, risco de duplicidade, coerência do BDI e suficiência da memória de cálculo.
A9: 6.1 CHECKLIST AVALIATIVO DE CONSISTÊNCIA
B10: Questão avaliativa | C10: Avaliação | D10: Nível de risco | E10: Comentários / evidências
B11: A metodologia adotada está claramente documentada? | C11: Não conforme | D11: Médio
B12: Os cálculos são rastreáveis desde as quantidades até o valor final? | C12: Não conforme | D12: Médio
B13: A memória de cálculo permite reproduzir os resultados? | C13: Não conforme | D13: Médio
B14: A referência de preços é compatível com o tipo de obra (reforma/nova/retrofit)? | C14: Conforme | D14: Alto
B15: O BDI adotado é compatível com o tipo de contratação e porte da obra? | C15: Conforme | D15: Alto
B16: O BDI inclui apenas componentes pertinentes (sem duplicidade)? | C16: Conforme | D16: Alto
B17: Há risco de dupla contagem entre composições unitárias e parcelas específicas? | C17: Não conforme | D17: Alto
B18: O uso do CUB (se houver) está restrito a hipóteses adequadas? | C18: Não conforme | D18: Alto
B19: Os incrementos sobre o CUB estão justificados tecnicamente? | C19: Conforme | D19: Baixo
B20: As cotações de mercado (se usadas) apresentam origem e data verificáveis? | C20: Conforme | D20: Baixo
B21: Há compatibilidade entre a data-base dos preços e a atualização adotada? | C21: Conforme | D21: Baixo
B22: A regionalização dos preços reflete as condições do RS / local da obra? | C22: Conforme | D22: Baixo
B23: Os parâmetros por m² (se usados) estão compatíveis com benchmarks do setor?
B24: A precificação guarda coerência com contratações similares do órgão?
B25: Existem componentes ausentes que deveriam estar contemplados?
B26: O valor global apresenta coerência com a complexidade e o escopo da obra?
B27: Há risco de superestimação / subestimação identificável?
B28: A consistência global da precificação é aceitável?

Sheet 7. Síntese
A6: ABA 7 — SÍNTESE CONCLUSIVA
A7: Quadro-resumo consolidando as informações. Alguns campos são preenchidos automaticamente a partir das abas anteriores; outros exigem interpretação e resumo do analista.
A9: 7.1 IDENTIFICAÇÃO CONSOLIDADA (preenchimento automático)
B10: Projeto / caso analisado: | C10: ='1. Identificação'!C10 -> 0
B11: Objeto: | C11: ='1. Identificação'!C11 -> 0
B12: Órgão / entidade: | C12: ='1. Identificação'!C12 -> 0
B13: Modalidade contratual: | C13: ='1. Identificação'!C15 -> 0
B14: Natureza da intervenção: | C14: ='1. Identificação'!C19 -> 0
B15: Valor total declarado (R$): | C15: ='1. Identificação'!C21 -> 0
B16: Fase analisada: | C16: ='1. Identificação'!C26 -> 0
B17: Data-base dos preços: | C17: ='1. Identificação'!C28 -> 0
A19: 7.2 INDICADORES DA ANÁLISE CRÍTICA (preenchimento automático)
B20: Total de metodologias marcadas como utilizadas: | C20: ='2. Metodologia'!C23 -> 0
B21: Itens 'Conforme' na análise crítica: | C21: =COUNTIF('6. Análise Crítica'!C11:C28,"Conforme") -> 7
B22: Itens 'Parcialmente conforme': | C22: =COUNTIF('6. Análise Crítica'!C11:C28,"Parcialmente conforme") -> 0
B23: Itens 'Não conforme': | C23: =COUNTIF('6. Análise Crítica'!C11:C28,"Não conforme") -> 5
B24: Itens com risco ALTO: | C24: =COUNTIF('6. Análise Crítica'!D11:D28,"Alto") -> 5
B25: Itens com risco MÉDIO: | C25: =COUNTIF('6. Análise Crítica'!D11:D28,"Médio") -> 3
B26: Itens com risco BAIXO: | C26: =COUNTIF('6. Análise Crítica'!D11:D28,"Baixo") -> 4
B27: Total de itens avaliados: | C27: =COUNTA('6. Análise Crítica'!C11:C28) -> 12
A30: 7.3 SÍNTESE INTERPRETATIVA (preenchimento pelo analista)
B31: Metodologia de precificação adotada (síntese):
B32: Referências de preços utilizadas (síntese):
B33: Principais parâmetros e componentes (síntese):
B34: Justificativa técnica apresentada (síntese):
B35: Avaliação da consistência metodológica (síntese):
B36: Fragilidades, lacunas e ressalvas identificadas:
B37: Recomendações e encaminhamentos sugeridos:
B38: Conclusão objetiva da análise:
A40: 7.4 PARECER GLOBAL DA PRECIFICAÇÃO
B41: Parecer global sobre a precificação analisada:

Sheet 8. Relatório
A6: ABA 8 — RELATÓRIO TÉCNICO (TEXTO-BASE)
A7: Texto gerado automaticamente a partir do preenchimento das demais abas. Destinado a subsidiar a elaboração de relatório, parecer ou nota técnica. Os textos podem ser copiados e editados livremente.
B9: RELATÓRIO TÉCNICO DE ANÁLISE DE PRECIFICAÇÃO DE OBRAS
B11: 1. IDENTIFICAÇÃO DO CASO
B12: ="Caso analisado: "&'1. Identificação'!C10&CHAR(10)&"Objeto: "&'1. Identificação'!C11&CHAR(10)&"Órgão/Entidade: "&'1. Identificação'!C12&CHAR(10)&"Modalidade contratual: "&'1. Identificação'!C15&CHAR(10)&"Natureza da intervenção: "&'1. Identificação'!C19&CHAR(10)&"Valor total declarado: "&TEXT('1. Identificação'!C21,"R$ #,##0.00")&CHAR(10)&"Fase analisada: "&'1. Identificação'!C26&CHAR(10)&"Documentos analisados: "&'1. Identificação'!C27&CHAR(10)&"Data-base dos preços: "&'1. Identificação'!C28 -> Caso analisado: Objeto: Órgão/Entidade: Modalidade contratual: Natureza da intervenção: Valor total declarado: R$ ,000 Fase analisada: Documentos analisados: Data-base dos preços:
B14: 2. METODOLOGIA DE PRECIFICAÇÃO ADOTADA
B15: ='7. Síntese'!C31 -> 0
B17: 3. REFERÊNCIAS DE PREÇOS UTILIZADAS
B18: ='7. Síntese'!C32 -> 0
B20: 4. PARÂMETROS E COMPONENTES EMPREGADOS
B21: ='7. Síntese'!C33 -> 0
B23: 5. JUSTIFICATIVA APRESENTADA PARA A PRECIFICAÇÃO
B24: ='7. Síntese'!C34 -> 0
B26: 6. ANÁLISE CRÍTICA DA CONSISTÊNCIA METODOLÓGICA
B27: ='7. Síntese'!C35 -> 0
B29: 7. FRAGILIDADES, LACUNAS E RESSALVAS IDENTIFICADAS
B30: ='7. Síntese'!C36 -> 0
B32: 8. RECOMENDAÇÕES E ENCAMINHAMENTOS
B33: ='7. Síntese'!C37 -> 0
B35: 9. CONCLUSÃO
B36: ="Parecer global: "&'7. Síntese'!C41&CHAR(10)&CHAR(10)&'7. Síntese'!C38 -> Parecer global:
B39: INDICADORES-CHAVE DA ANÁLISE
B40: ="Total de itens avaliados na análise crítica: "&'7. Síntese'!C27&CHAR(10)&"Itens conformes: "&'7. Síntese'!C21&CHAR(10)&"Itens parcialmente conformes: "&'7. Síntese'!C22&CHAR(10)&"Itens não conformes: "&'7. Síntese'!C23&CHAR(10)&"Itens com risco alto: "&'7. Síntese'!C24&CHAR(10)&"Itens com risco médio: "&'7. Síntese'!C25&CHAR(10)&"Itens com risco baixo: "&'7. Síntese'!C26 -> Total de itens avaliados na análise crítica: 12 Itens conformes: 7 Itens parcialmente conformes: 0 Itens não conformes: 5 Itens com risco alto: 5 Itens com risco médio: 3 Itens com risco baixo: 4
B42: CAGE/SEFAZ-RS — Texto gerado automaticamente a partir da ferramenta padronizada. Recomenda-se revisão pelo analista antes da emissão formal.

Sheet 9. Dashboard
B6: Visão Consolidada da Precificação
B7: Indicadores agregados do checklist da Aba 6 — conforme preenchimento.
B10: TOTAL DE ITENS | D10: CONFORMES | F10: PARCIALMENTE CONFORMES | H10: NÃO CONFORMES
B11: ='7. Síntese'!C27 -> 12 | D11: ='7. Síntese'!C21 -> 7 | F11: ='7. Síntese'!C22 -> 0 | H11: ='7. Síntese'!C23 -> 5
B12: avaliados | D12: =TEXT(IFERROR('7. Síntese'!C21/'7. Síntese'!C27,0),"0%")&" do total" -> 58% do total | F12: =TEXT(IFERROR('7. Síntese'!C22/'7. Síntese'!C27,0),"0%")&" do total" -> 0% do total | H12: =TEXT(IFERROR('7. Síntese'!C23/'7. Síntese'!C27,0),"0%")&" do total" -> 42% do total
B16: 01 | C16: MATRIZ AVALIAÇÃO × RISCO
B17: Cor = severidade da posição (avaliação × risco). Vermelho escuro = crítico máximo, independente do valor.
C19: Baixo | D19: Médio | E19: Alto | F19: Não identificado | G19: Total
B20: Conforme | C20: =COUNTIFS('6. Análise Crítica'!C11:C28,"Conforme",'6. Análise Crítica'!D11:D28,"Baixo") -> 4 | D20: =COUNTIFS('6. Análise Crítica'!C11:C28,"Conforme",'6. Análise Crítica'!D11:D28,"Médio") -> 0 | E20: =COUNTIFS('6. Análise Crítica'!C11:C28,"Conforme",'6. Análise Crítica'!D11:D28,"Alto") -> 3 | F20: =COUNTIFS('6. Análise Crítica'!C11:C28,"Conforme",'6. Análise Crítica'!D11:D28,"Não identificado") -> 0 | G20: =SUM(C20:F20) -> 7
B21: Parcialmente conforme | C21: =COUNTIFS('6. Análise Crítica'!C11:C28,"Parcialmente conforme",'6. Análise Crítica'!D11:D28,"Baixo") -> 0 | D21: =COUNTIFS('6. Análise Crítica'!C11:C28,"Parcialmente conforme",'6. Análise Crítica'!D11:D28,"Médio") -> 0 | E21: =COUNTIFS('6. Análise Crítica'!C11:C28,"Parcialmente conforme",'6. Análise Crítica'!D11:D28,"Alto") -> 0 | F21: =COUNTIFS('6. Análise Crítica'!C11:C28,"Parcialmente conforme",'6. Análise Crítica'!D11:D28,"Não identificado") -> 0 | G21: =SUM(C21:F21) -> 0
B22: Não conforme | C22: =COUNTIFS('6. Análise Crítica'!C11:C28,"Não conforme",'6. Análise Crítica'!D11:D28,"Baixo") -> 0 | D22: =COUNTIFS('6. Análise Crítica'!C11:C28,"Não conforme",'6. Análise Crítica'!D11:D28,"Médio") -> 3 | E22: =COUNTIFS('6. Análise Crítica'!C11:C28,"Não conforme",'6. Análise Crítica'!D11:D28,"Alto") -> 2 | F22: =COUNTIFS('6. Análise Crítica'!C11:C28,"Não conforme",'6. Análise Crítica'!D11:D28,"Não identificado") -> 0 | G22: =SUM(C22:F22) -> 5
B23: Não aplicável | C23: =COUNTIFS('6. Análise Crítica'!C11:C28,"Não aplicável",'6. Análise Crítica'!D11:D28,"Baixo") -> 0 | D23: =COUNTIFS('6. Análise Crítica'!C11:C28,"Não aplicável",'6. Análise Crítica'!D11:D28,"Médio") -> 0 | E23: =COUNTIFS('6. Análise Crítica'!C11:C28,"Não aplicável",'6. Análise Crítica'!D11:D28,"Alto") -> 0 | F23: =COUNTIFS('6. Análise Crítica'!C11:C28,"Não aplicável",'6. Análise Crítica'!D11:D28,"Não identificado") -> 0 | G23: =SUM(C23:F23) -> 0
B24: Total | C24: =SUM(C20:C23) -> 4 | D24: =SUM(D20:D23) -> 3 | E24: =SUM(E20:E23) -> 5 | F24: =SUM(F20:F23) -> 0 | G24: =SUM(G20:G23) -> 12
B26: 02 | C26: DISTRIBUIÇÕES AGREGADAS
B27: Visão por avaliação e por nível de risco — para leitura rápida do agregado.
B29: Avaliação | C29: Itens | E29: Nível de risco | F29: Itens
B30: Conforme | C30: ='7. Síntese'!C21 -> 7 | E30: Baixo | F30: ='7. Síntese'!C26 -> 4
B31: Parcialmente conforme | C31: ='7. Síntese'!C22 -> 0 | E31: Médio | F31: ='7. Síntese'!C25 -> 3
B32: Não conforme | C32: ='7. Síntese'!C23 -> 5 | E32: Alto | F32: ='7. Síntese'!C24 -> 5
B33: Não aplicável | C33: =COUNTIF('6. Análise Crítica'!C11:C28,"Não aplicável") -> 0 | E33: Não identificado | F33: =COUNTIF('6. Análise Crítica'!D11:D28,"Não identificado") -> 0
B36: Por avaliação | E36: Por nível de risco
B53: 03 | C53: ITENS PRIORITÁRIOS
B54: Itens classificados como Não Conforme ou com Risco Alto — atualizam automaticamente conforme preenchimento da Aba 6.
B56: Questão avaliativa | F56: Avaliação | G56: Risco | H56: Comentários / evidências
B57: =_xlfn._xlws.FILTER('6. Análise Crítica'!B11:B28,('6. Análise Crítica'!C11:C28="Não conforme")+('6. Análise Crítica'!D11:D28="Alto"),"Nenhum item prioritário identificado.") -> A metodologia adotada está claramente documentada? | F57: =_xlfn._xlws.FILTER('6. Análise Crítica'!C11:C28,('6. Análise Crítica'!C11:C28="Não conforme")+('6. Análise Crítica'!D11:D28="Alto"),"") -> Não conforme | G57: =_xlfn._xlws.FILTER('6. Análise Crítica'!D11:D28,('6. Análise Crítica'!C11:C28="Não conforme")+('6. Análise Crítica'!D11:D28="Alto"),"") -> Médio | H57: =_xlfn._xlws.FILTER('6. Análise Crítica'!E11:E28,('6. Análise Crítica'!C11:C28="Não conforme")+('6. Análise Crítica'!D11:D28="Alto"),"") -> 0
B71: Fonte: Aba 6 (entrada) → Aba 7 (indicadores) → Aba 9 (consolidação visual). CAGE/SEFAZ-RS.
